multilogging/__init__.py
multilogging-1.0.2.dist-info/METADATA
multilogging-1.0.2.dist-info/WHEEL
multilogging-1.0.2.dist-info/top_level.txt
multilogging-1.0.2.dist-info/RECORD
