Metadata-Version: 2.1
Name: multilogging
Version: 1.0.2
Summary: 分布式 loguru
Home-page: https://gitee.com/unvisitor/multilogging
Author: Night Resurgent <fu050409@163.com>
Author-email: fu050409@163.com
License: Apache-2.0
Project-URL: Bug Tracker, https://gitee.com/unvisitor/multilogging/issues
Classifier: Programming Language :: Python :: 3
Classifier: License :: OSI Approved :: Apache Software License
Classifier: Operating System :: OS Independent
Requires-Python: >=3
Requires-Dist: loguru
